pandas_cli/__init__.py
pandas_cli/__main__.py
pandas_cli-0.3.0.dist-info/METADATA
pandas_cli-0.3.0.dist-info/WHEEL
pandas_cli-0.3.0.dist-info/entry_points.txt
pandas_cli-0.3.0.dist-info/RECORD
